fgmutils/__init__.py
fgmutils/calculations.py
fgmutils/classification.py
fgmutils/dataops.py
fgmutils/evaluation.py
fgmutils/metrics.py
fgmutils/prediction.py
fgmutils/project.py
fgmutils/statistics.py
fgmutils/utils.py
fgmutils/volume.py
fgmutils-1.0.0.dist-info/licenses/LICENSE
fgmutils-1.0.0.dist-info/METADATA
fgmutils-1.0.0.dist-info/WHEEL
fgmutils-1.0.0.dist-info/top_level.txt
fgmutils-1.0.0.dist-info/RECORD
