Metadata-Version: 2.4
Name: fgmutils
Version: 1.0.0
Summary: Forest Growth Model Utilities
Author: Ana Paula Simiqueli, Gilson Fernandes da Silva, Miqueias Fernandes, Wagner Amorim da Silva Altoe
Author-email: Clayton Vieira Fraga Filho <forestgrowthsoftware@gmail.com>
License: GPL-2
Project-URL: Homepage, https://github.com/forestgrowthsoftware/fgmutils
Project-URL: Issues, https://github.com/forestgrowthsoftware/fgmutils/issues
Keywords: Forest Inventory,Growth Models
Classifier: Development Status :: 2 - Pre-Alpha
Classifier: Intended Audience :: Science/Research
Classifier: Topic :: Scientific/Engineering
Classifier: License :: OSI Approved :: GNU General Public License v2 (GPLv2)
Classifier: Programming Language :: Python :: 3
Classifier: Programming Language :: Python :: 3.9
Classifier: Programming Language :: Python :: 3.10
Classifier: Programming Language :: Python :: 3.11
Classifier: Programming Language :: Python :: 3.12
Requires-Python: >=3.9
License-File: LICENSE
Requires-Dist: numpy>=1.23
Requires-Dist: pandas>=2.0
Requires-Dist: statsmodels>=0.14
Provides-Extra: dev
Requires-Dist: pytest>=7.4; extra == "dev"
Requires-Dist: pytest-cov>=4.1; extra == "dev"
Requires-Dist: ruff>=0.2; extra == "dev"
Requires-Dist: black>=24.2; extra == "dev"
Dynamic: license-file
